redress/__init__.py
redress/circuit.py
redress/classify.py
redress/cli.py
redress/config.py
redress/errors.py
redress/events.py
redress/extras.py
redress/metrics.py
redress/sleep.py
redress/strategies.py
redress/contrib/otel.py
redress/contrib/pyodbc.py
redress/policy/__init__.py
redress/policy/async_policy.py
redress/policy/base.py
redress/policy/container.py
redress/policy/context.py
redress/policy/decorator.py
redress/policy/policy.py
redress/policy/policy_helpers.py
redress/policy/retry.py
redress/policy/retry_async.py
redress/policy/retry_helpers.py
redress/policy/retry_sync.py
redress/policy/state.py
redress/policy/types.py
redress/policy/wrappers.py
redress/policy/runner/__init__.py
redress/policy/runner/async_core.py
redress/policy/runner/async_runner.py
redress/policy/runner/sync_core.py
redress/policy/runner/sync_runner.py
redress/policy/runner/timeline.py
redress/py.typed
redress-1.1.0.dist-info/METADATA
redress-1.1.0.dist-info/WHEEL
redress-1.1.0.dist-info/entry_points.txt
redress-1.1.0.dist-info/licenses/LICENSE
redress-1.1.0.dist-info/RECORD
